crosscompute_views_map/__init__.py
crosscompute_views_map/constants.py
crosscompute_views_map/assets/deck-screengrid-output-header.js
crosscompute_views_map/assets/deck-screengrid-output.js
crosscompute_views_map/assets/map.css
crosscompute_views_map/assets/mapbox-header.js
crosscompute_views_map/assets/mapbox-location-input-header.js
crosscompute_views_map/assets/mapbox-location-input.html
crosscompute_views_map/assets/mapbox-location-input.js
crosscompute_views_map/assets/mapbox-output-header.js
crosscompute_views_map/assets/mapbox-output.js
crosscompute_views_map/assets/mapbox.html
crosscompute_views_map/routines/__init__.py
crosscompute_views_map/routines/asset.py
crosscompute_views_map/routines/variable.py
crosscompute_views_map-0.2.2.dist-info/LICENSE.md
crosscompute_views_map-0.2.2.dist-info/METADATA
crosscompute_views_map-0.2.2.dist-info/WHEEL
crosscompute_views_map-0.2.2.dist-info/entry_points.txt
crosscompute_views_map-0.2.2.dist-info/top_level.txt
crosscompute_views_map-0.2.2.dist-info/zip-safe
crosscompute_views_map-0.2.2.dist-info/RECORD
